{"$schema":"https://json.openmrs.org/routes.schema.json","backendDependencies":{"fhir2":">=1.2","webservices.rest":"^2.24.0"},"extensions":[{"component":"imagingOrdersLink","name":"imaging-orders-link","slot":"homepage-dashboard-slot","meta":{"name":"imaging-orders","title":"imaging-orders","slot":"imaging-dashboard-slot"}},{"component":"root","name":"imaging-dashboard-root","slot":"imaging-dashboard-slot"},{"name":"imaging-order-panel","component":"imagingOrderPanel","slot":"order-basket-slot","order":3}],"workspaces2":[{"name":"add-imaging-order","type":"order","title":"Add Imaging order","component":"addImagingOrderWorkspace","window":"patient-chart-order-basket"},{"name":"imaging-report-form","title":"Imaging Report Form","type":"form","component":"imagingReportForm","window":"imaging-orders-window"},{"name":"imaging-review-form","type":"order","title":"Review form","component":"imagingReviewForm","window":"imaging-orders-window"},{"name":"imagingResultFormWorkspace","component":"imagingResultFormWorkspace","window":"imaging-orders-window"}],"workspaceWindows2":[{"name":"imaging-orders-window","group":"imaging-orders-group"}],"workspaceGroups2":[{"name":"imaging-orders-group","overlay":true}],"modals":[{"name":"reject-imaging-order-modal","component":"rejectImagingOrderModal"},{"name":"add-imaging-to-work-list-modal","component":"addImagingToWorkListModal"},{"name":"amend-imaging-order-modal","component":"amendModal"},{"name":"print-preview-Report-modal","component":"printReportModal"}],"pages":[{"component":"root","route":"imaging"}],"version":"4.0.6-pre.26"}